.gitignore
CHANGELOG.md
LICENSE.txt
README.rst
environment.yml
nbval_sanitize.cfg
pytest.ini
setup.py
test_requirements.txt
dmslogo/__init__.py
dmslogo/colorschemes.py
dmslogo/facet.py
dmslogo/line.py
dmslogo/logo.py
dmslogo/utils.py
dmslogo.egg-info/PKG-INFO
dmslogo.egg-info/SOURCES.txt
dmslogo.egg-info/dependency_links.txt
dmslogo.egg-info/requires.txt
dmslogo.egg-info/top_level.txt
dmslogo/ttf_fonts/Comic Sans MS.ttf
dmslogo/ttf_fonts/DejaVuSansMonoBold_SeqLogo.ttf
dmslogo/ttf_fonts/README.md
docs/Makefile
docs/README.rst
docs/acknowledgments.rst
docs/basic_example.nblink
docs/conf.py
docs/doc_requirements.txt
docs/examples.rst
docs/index.rst
docs/installation.rst
docs/negative_values.nblink
docs/overlays.nblink
docs/package_index.rst
docs/set_ylims.nblink
docs/_static/BloomLogo.jpg
docs/_static/dmslogo_comic_sans.png
docs/_static/facet_plot_example.png
notebooks/.gitignore
notebooks/README.md
notebooks/basic_example.ipynb
notebooks/negative_values.ipynb
notebooks/overlays.ipynb
notebooks/set_ylims.ipynb
notebooks/input_files/BG505_to_HXB2.csv
notebooks/input_files/HA_serum_diffsel.csv
notebooks/input_files/summary_PG9-medianmutfracsurvive.csv
notebooks/input_files/summary_PGT145-medianmutfracsurvive.csv