Metadata-Version: 2.1
Name: dmslogo
Version: 0.7.0
Summary: Logo plots of deep mutational scanning (DMS) data
Home-page: https://github.com/jbloomlab/dmslogo
Download-URL: https://github.com/jbloomlab/dmslogo/tarball/0.7.0
Author: Jesse Bloom
Author-email: jbloom@fredhutch.org
License: GPLv3
Platform: Linux and Mac OS X.
License-File: LICENSE.txt
